Metadata-Version: 2.1
Name: dnevnikru-aio
Version: 1.0
Summary: dnevnik.ru unofficial API asyncio parser
Home-page: https://github.com/vypivshiy/dnevnikru-aio
Author: vypivshiy
Author-email: 
License: GPL3
Platform: UNKNOWN
